binalyze/__init__.py
binalyze/air/__init__.py
binalyze/air/base.py
binalyze/air/client.py
binalyze/air/config.py
binalyze/air/constants.py
binalyze/air/env_config.py
binalyze/air/exceptions.py
binalyze/air/filter_builder.py
binalyze/air/http_client.py
binalyze/air/logging.py
binalyze/air/sdk.py
binalyze/air/apis/__init__.py
binalyze/air/apis/acquisitions.py
binalyze/air/apis/api_tokens.py
binalyze/air/apis/assets.py
binalyze/air/apis/audit_logs.py
binalyze/air/apis/auth.py
binalyze/air/apis/auto_asset_tags.py
binalyze/air/apis/backup.py
binalyze/air/apis/baseline.py
binalyze/air/apis/cases.py
binalyze/air/apis/cloud_forensics.py
binalyze/air/apis/event_subscription.py
binalyze/air/apis/evidence.py
binalyze/air/apis/interact.py
binalyze/air/apis/investigation_hub.py
binalyze/air/apis/license.py
binalyze/air/apis/logger.py
binalyze/air/apis/multipart_upload.py
binalyze/air/apis/notifications.py
binalyze/air/apis/organizations.py
binalyze/air/apis/params.py
binalyze/air/apis/policies.py
binalyze/air/apis/preset_filters.py
binalyze/air/apis/recent_activities.py
binalyze/air/apis/relay_server.py
binalyze/air/apis/settings.py
binalyze/air/apis/tasks.py
binalyze/air/apis/triage.py
binalyze/air/apis/user_management.py
binalyze/air/apis/webhook_executions.py
binalyze/air/apis/webhooks.py
binalyze/air/commands/__init__.py
binalyze/air/commands/acquisitions.py
binalyze/air/commands/api_tokens.py
binalyze/air/commands/assets.py
binalyze/air/commands/auth.py
binalyze/air/commands/auto_asset_tags.py
binalyze/air/commands/backup.py
binalyze/air/commands/baseline.py
binalyze/air/commands/cases.py
binalyze/air/commands/cloud_forensics.py
binalyze/air/commands/event_subscription.py
binalyze/air/commands/evidences.py
binalyze/air/commands/interact.py
binalyze/air/commands/investigation_hub.py
binalyze/air/commands/license.py
binalyze/air/commands/logger.py
binalyze/air/commands/multipart_upload.py
binalyze/air/commands/notifications.py
binalyze/air/commands/organizations.py
binalyze-2.0.3.dist-info/METADATA
binalyze-2.0.3.dist-info/WHEEL
binalyze-2.0.3.dist-info/entry_points.txt
binalyze-2.0.3.dist-info/top_level.txt
binalyze-2.0.3.dist-info/RECORD
