Metadata-Version: 2.4
Name: binalyze
Version: 2.0.3
Summary: Complete Python SDK for Binalyze Products - AIR, Fleet, and more
Home-page: https://github.com/binalyze/python-sdk
Author: Binalyze
Author-email: support@binalyze.com
Project-URL: Bug Reports, https://github.com/binalyze/python-sdk/issues
Project-URL: Source, https://github.com/binalyze/python-sdk
Project-URL: Documentation, https://github.com/binalyze/python-sdk/blob/main/README.md
Project-URL: Binalyze, https://binalyze.com
Project-URL: AIR Product, https://binalyze.com/products/air/
Keywords: binalyze air fleet forensics security api sdk digital-forensics incident-response dfir
Classifier: Development Status :: 5 - Production/Stable
Classifier: Intended Audience :: Developers
Classifier: Intended Audience :: Information Technology
Classifier: Intended Audience :: System Administrators
Classifier: License :: OSI Approved :: MIT License
Classifier: Operating System :: OS Independent
Classifier: Programming Language :: Python :: 3
Classifier: Programming Language :: Python :: 3.8
Classifier: Programming Language :: Python :: 3.9
Classifier: Programming Language :: Python :: 3.10
Classifier: Programming Language :: Python :: 3.11
Classifier: Programming Language :: Python :: 3.12
Classifier: Topic :: Security
Classifier: Topic :: System :: Systems Administration
Classifier: Topic :: Software Development :: Libraries :: Python Modules
Classifier: Topic :: Software Development :: Libraries :: Application Frameworks
Requires-Python: >=3.8
Requires-Dist: requests>=2.25.1
Requires-Dist: pydantic>=2.0.0
Requires-Dist: typing-extensions>=4.0.0
Requires-Dist: python-dateutil>=2.8.0
Requires-Dist: urllib3>=1.26.0
Provides-Extra: dev
Requires-Dist: pytest>=6.0; extra == "dev"
Requires-Dist: pytest-asyncio; extra == "dev"
Requires-Dist: black; extra == "dev"
Requires-Dist: isort; extra == "dev"
Requires-Dist: mypy; extra == "dev"
Requires-Dist: flake8; extra == "dev"
Requires-Dist: pylint; extra == "dev"
Provides-Extra: testing
Requires-Dist: pytest>=6.0; extra == "testing"
Requires-Dist: pytest-cov; extra == "testing"
Requires-Dist: pytest-mock; extra == "testing"
Provides-Extra: env
Requires-Dist: python-dotenv>=0.19.0; extra == "env"
Provides-Extra: full
Requires-Dist: python-dotenv>=0.19.0; extra == "full"
Requires-Dist: pytest>=6.0; extra == "full"
Requires-Dist: pytest-cov; extra == "full"
Requires-Dist: pytest-mock; extra == "full"
Requires-Dist: black; extra == "full"
Requires-Dist: isort; extra == "full"
Requires-Dist: mypy; extra == "full"
Requires-Dist: flake8; extra == "full"
Requires-Dist: pylint; extra == "full"
Dynamic: author
Dynamic: author-email
Dynamic: classifier
Dynamic: description
Dynamic: description-content-type
Dynamic: home-page
Dynamic: keywords
Dynamic: project-url
Dynamic: provides-extra
Dynamic: requires-dist
Dynamic: requires-python
Dynamic: summary
